Metadata-Version: 2.4
Name: juan_almeida_image_processing
Version: 0.0.1
Summary: Image Processing Package using scikit-image
Author-email: JUAN <juanhl_almeida@hotmail.com>
Project-URL: Homepage, https://github.com/juanhlalmeida/dio-image-processing-package.git
Requires-Python: >=3.8
Requires-Dist: scikit-image
Requires-Dist: numpy
Requires-Dist: matplotlib
